{
  "type": "Program",
  "body": [
    {
      "type": "ExpressionStatement",
      "expression": {
        "type": "Literal",
        "value": "use strict",
        "raw": "'use strict'",
        "range": [
          0,
          12
        ],
        "loc": {
          "start": {
            "line": 1,
            "column": 0
          },
          "end": {
            "line": 1,
            "column": 12
          }
        }
      },
      "range": [
        0,
        13
      ],
      "loc": {
        "start": {
          "line": 1,
          "column": 0
        },
        "end": {
          "line": 1,
          "column": 13
        }
      }
    },
    {
      "type": "ImportDeclaration",
      "specifiers": [
        {
          "type": "ImportDefaultSpecifier",
          "local": {
            "type": "Identifier",
            "name": "BulkBuilder",
            "range": [
              24,
              35
            ],
            "loc": {
              "start": {
                "line": 3,
                "column": 7
              },
              "end": {
                "line": 3,
                "column": 18
              }
            }
          },
          "range": [
            24,
            35
          ],
          "loc": {
            "start": {
              "line": 3,
              "column": 7
            },
            "end": {
              "line": 3,
              "column": 18
            }
          }
        }
      ],
      "source": {
        "type": "Literal",
        "value": "./BulkBuilder",
        "raw": "'./BulkBuilder'",
        "range": [
          41,
          56
        ],
        "loc": {
          "start": {
            "line": 3,
            "column": 24
          },
          "end": {
            "line": 3,
            "column": 39
          }
        }
      },
      "range": [
        17,
        57
      ],
      "loc": {
        "start": {
          "line": 3,
          "column": 0
        },
        "end": {
          "line": 3,
          "column": 40
        }
      },
      "trailingComments": [
        {
          "type": "Block",
          "value": "*\r\n * Json builder. This builder give you the necessary tools to create a json bulk using our OpenGate REST.\r\n ",
          "range": [
            61,
            176
          ],
          "loc": {
            "start": {
              "line": 5,
              "column": 0
            },
            "end": {
              "line": 7,
              "column": 3
            }
          }
        }
      ]
    },
    {
      "type": "ExportDefaultDeclaration",
      "declaration": {
        "type": "ClassDeclaration",
        "id": {
          "type": "Identifier",
          "name": "JsonFlattenedBulkBuilder",
          "range": [
            199,
            223
          ],
          "loc": {
            "start": {
              "line": 8,
              "column": 21
            },
            "end": {
              "line": 8,
              "column": 45
            }
          }
        },
        "superClass": {
          "type": "Identifier",
          "name": "BulkBuilder",
          "range": [
            232,
            243
          ],
          "loc": {
            "start": {
              "line": 8,
              "column": 54
            },
            "end": {
              "line": 8,
              "column": 65
            }
          }
        },
        "body": {
          "type": "ClassBody",
          "body": [
            {
              "type": "MethodDefinition",
              "key": {
                "type": "Identifier",
                "name": "constructor",
                "range": [
                  754,
                  765
                ],
                "loc": {
                  "start": {
                    "line": 16,
                    "column": 4
                  },
                  "end": {
                    "line": 16,
                    "column": 15
                  }
                }
              },
              "value": {
                "type": "FunctionExpression",
                "id": null,
                "params": [
                  {
                    "type": "Identifier",
                    "name": "ogapi",
                    "range": [
                      766,
                      771
                    ],
                    "loc": {
                      "start": {
                        "line": 16,
                        "column": 16
                      },
                      "end": {
                        "line": 16,
                        "column": 21
                      }
                    }
                  },
                  {
                    "type": "Identifier",
                    "name": "organization",
                    "range": [
                      773,
                      785
                    ],
                    "loc": {
                      "start": {
                        "line": 16,
                        "column": 23
                      },
                      "end": {
                        "line": 16,
                        "column": 35
                      }
                    }
                  },
                  {
                    "type": "Identifier",
                    "name": "resource",
                    "range": [
                      787,
                      795
                    ],
                    "loc": {
                      "start": {
                        "line": 16,
                        "column": 37
                      },
                      "end": {
                        "line": 16,
                        "column": 45
                      }
                    }
                  },
                  {
                    "type": "Identifier",
                    "name": "timeout",
                    "range": [
                      797,
                      804
                    ],
                    "loc": {
                      "start": {
                        "line": 16,
                        "column": 47
                      },
                      "end": {
                        "line": 16,
                        "column": 54
                      }
                    }
                  }
                ],
                "body": {
                  "type": "BlockStatement",
                  "body": [
                    {
                      "type": "ExpressionStatement",
                      "expression": {
                        "type": "CallExpression",
                        "callee": {
                          "type": "Super",
                          "range": [
                            817,
                            822
                          ],
                          "loc": {
                            "start": {
                              "line": 17,
                              "column": 8
                            },
                            "end": {
                              "line": 17,
                              "column": 13
                            }
                          }
                        },
                        "arguments": [
                          {
                            "type": "Identifier",
                            "name": "ogapi",
                            "range": [
                              823,
                              828
                            ],
                            "loc": {
                              "start": {
                                "line": 17,
                                "column": 14
                              },
                              "end": {
                                "line": 17,
                                "column": 19
                              }
                            }
                          },
                          {
                            "type": "BinaryExpression",
                            "operator": "+",
                            "left": {
                              "type": "BinaryExpression",
                              "operator": "+",
                              "left": {
                                "type": "BinaryExpression",
                                "operator": "+",
                                "left": {
                                  "type": "Literal",
                                  "value": "provision/organizations/",
                                  "raw": "'provision/organizations/'",
                                  "range": [
                                    830,
                                    856
                                  ],
                                  "loc": {
                                    "start": {
                                      "line": 17,
                                      "column": 21
                                    },
                                    "end": {
                                      "line": 17,
                                      "column": 47
                                    }
                                  }
                                },
                                "right": {
                                  "type": "Identifier",
                                  "name": "organization",
                                  "range": [
                                    859,
                                    871
                                  ],
                                  "loc": {
                                    "start": {
                                      "line": 17,
                                      "column": 50
                                    },
                                    "end": {
                                      "line": 17,
                                      "column": 62
                                    }
                                  }
                                },
                                "range": [
                                  830,
                                  871
                                ],
                                "loc": {
                                  "start": {
                                    "line": 17,
                                    "column": 21
                                  },
                                  "end": {
                                    "line": 17,
                                    "column": 62
                                  }
                                }
                              },
                              "right": {
                                "type": "Literal",
                                "value": "/bulk/",
                                "raw": "'/bulk/'",
                                "range": [
                                  874,
                                  882
                                ],
                                "loc": {
                                  "start": {
                                    "line": 17,
                                    "column": 65
                                  },
                                  "end": {
                                    "line": 17,
                                    "column": 73
                                  }
                                }
                              },
                              "range": [
                                830,
                                882
                              ],
                              "loc": {
                                "start": {
                                  "line": 17,
                                  "column": 21
                                },
                                "end": {
                                  "line": 17,
                                  "column": 73
                                }
                              }
                            },
                            "right": {
                              "type": "Identifier",
                              "name": "resource",
                              "range": [
                                885,
                                893
                              ],
                              "loc": {
                                "start": {
                                  "line": 17,
                                  "column": 76
                                },
                                "end": {
                                  "line": 17,
                                  "column": 84
                                }
                              }
                            },
                            "range": [
                              830,
                              893
                            ],
                            "loc": {
                              "start": {
                                "line": 17,
                                "column": 21
                              },
                              "end": {
                                "line": 17,
                                "column": 84
                              }
                            }
                          },
                          {
                            "type": "Literal",
                            "value": "application/json",
                            "raw": "'application/json'",
                            "range": [
                              895,
                              913
                            ],
                            "loc": {
                              "start": {
                                "line": 17,
                                "column": 86
                              },
                              "end": {
                                "line": 17,
                                "column": 104
                              }
                            }
                          },
                          {
                            "type": "Identifier",
                            "name": "timeout",
                            "range": [
                              915,
                              922
                            ],
                            "loc": {
                              "start": {
                                "line": 17,
                                "column": 106
                              },
                              "end": {
                                "line": 17,
                                "column": 113
                              }
                            }
                          }
                        ],
                        "range": [
                          817,
                          923
                        ],
                        "loc": {
                          "start": {
                            "line": 17,
                            "column": 8
                          },
                          "end": {
                            "line": 17,
                            "column": 114
                          }
                        }
                      },
                      "range": [
                        817,
                        924
                      ],
                      "loc": {
                        "start": {
                          "line": 17,
                          "column": 8
                        },
                        "end": {
                          "line": 17,
                          "column": 115
                        }
                      }
                    },
                    {
                      "type": "ExpressionStatement",
                      "expression": {
                        "type": "CallExpression",
                        "callee": {
                          "type": "MemberExpression",
                          "computed": false,
                          "object": {
                            "type": "ThisExpression",
                            "range": [
                              934,
                              938
                            ],
                            "loc": {
                              "start": {
                                "line": 18,
                                "column": 8
                              },
                              "end": {
                                "line": 18,
                                "column": 12
                              }
                            }
                          },
                          "property": {
                            "type": "Identifier",
                            "name": "_setUrlParameters",
                            "range": [
                              939,
                              956
                            ],
                            "loc": {
                              "start": {
                                "line": 18,
                                "column": 13
                              },
                              "end": {
                                "line": 18,
                                "column": 30
                              }
                            }
                          },
                          "range": [
                            934,
                            956
                          ],
                          "loc": {
                            "start": {
                              "line": 18,
                              "column": 8
                            },
                            "end": {
                              "line": 18,
                              "column": 30
                            }
                          }
                        },
                        "arguments": [
                          {
                            "type": "ObjectExpression",
                            "properties": [
                              {
                                "type": "Property",
                                "key": {
                                  "type": "Identifier",
                                  "name": "flattened",
                                  "range": [
                                    972,
                                    981
                                  ],
                                  "loc": {
                                    "start": {
                                      "line": 19,
                                      "column": 12
                                    },
                                    "end": {
                                      "line": 19,
                                      "column": 21
                                    }
                                  }
                                },
                                "value": {
                                  "type": "Literal",
                                  "value": true,
                                  "raw": "true",
                                  "range": [
                                    983,
                                    987
                                  ],
                                  "loc": {
                                    "start": {
                                      "line": 19,
                                      "column": 23
                                    },
                                    "end": {
                                      "line": 19,
                                      "column": 27
                                    }
                                  }
                                },
                                "kind": "init",
                                "method": false,
                                "shorthand": false,
                                "computed": false,
                                "range": [
                                  972,
                                  987
                                ],
                                "loc": {
                                  "start": {
                                    "line": 19,
                                    "column": 12
                                  },
                                  "end": {
                                    "line": 19,
                                    "column": 27
                                  }
                                }
                              }
                            ],
                            "range": [
                              957,
                              998
                            ],
                            "loc": {
                              "start": {
                                "line": 18,
                                "column": 31
                              },
                              "end": {
                                "line": 20,
                                "column": 9
                              }
                            }
                          }
                        ],
                        "range": [
                          934,
                          999
                        ],
                        "loc": {
                          "start": {
                            "line": 18,
                            "column": 8
                          },
                          "end": {
                            "line": 20,
                            "column": 10
                          }
                        }
                      },
                      "range": [
                        934,
                        1000
                      ],
                      "loc": {
                        "start": {
                          "line": 18,
                          "column": 8
                        },
                        "end": {
                          "line": 20,
                          "column": 11
                        }
                      }
                    }
                  ],
                  "range": [
                    806,
                    1007
                  ],
                  "loc": {
                    "start": {
                      "line": 16,
                      "column": 56
                    },
                    "end": {
                      "line": 21,
                      "column": 5
                    }
                  }
                },
                "generator": false,
                "expression": false,
                "range": [
                  765,
                  1007
                ],
                "loc": {
                  "start": {
                    "line": 16,
                    "column": 15
                  },
                  "end": {
                    "line": 21,
                    "column": 5
                  }
                }
              },
              "kind": "constructor",
              "computed": false,
              "range": [
                754,
                1007
              ],
              "loc": {
                "start": {
                  "line": 16,
                  "column": 4
                },
                "end": {
                  "line": 21,
                  "column": 5
                }
              },
              "leadingComments": [
                {
                  "type": "Block",
                  "value": "*\r\n     * @param {InternalOpenGateAPI} ogapi - required field. This is ogapi instance\r\n     * @param {string} organization - required field. This is the organization name where entities will be created, updated or deleted\r\n     * @param {resource} resource - required field. This is the resource used for the bulk provision\r\n     * @param {number} [timeout] - timeout in millisecons. The request will have a specific time out if it will be exceeded then the promise throw an exception\r\n     ",
                  "range": [
                    253,
                    748
                  ],
                  "loc": {
                    "start": {
                      "line": 10,
                      "column": 4
                    },
                    "end": {
                      "line": 15,
                      "column": 7
                    }
                  }
                }
              ],
              "static": false
            }
          ],
          "range": [
            244,
            1012
          ],
          "loc": {
            "start": {
              "line": 8,
              "column": 66
            },
            "end": {
              "line": 23,
              "column": 1
            }
          }
        },
        "range": [
          193,
          1012
        ],
        "loc": {
          "start": {
            "line": 8,
            "column": 15
          },
          "end": {
            "line": 23,
            "column": 1
          }
        },
        "leadingComments": [
          {
            "type": "Block",
            "value": "*\r\n * Json builder. This builder give you the necessary tools to create a json bulk using our OpenGate REST.\r\n ",
            "range": [
              61,
              176
            ],
            "loc": {
              "start": {
                "line": 5,
                "column": 0
              },
              "end": {
                "line": 7,
                "column": 3
              }
            }
          }
        ],
        "trailingComments": []
      },
      "range": [
        178,
        1012
      ],
      "loc": {
        "start": {
          "line": 8,
          "column": 0
        },
        "end": {
          "line": 23,
          "column": 1
        }
      },
      "leadingComments": [
        {
          "type": "Block",
          "value": "*\r\n * Json builder. This builder give you the necessary tools to create a json bulk using our OpenGate REST.\r\n ",
          "range": [
            61,
            176
          ],
          "loc": {
            "start": {
              "line": 5,
              "column": 0
            },
            "end": {
              "line": 7,
              "column": 3
            }
          }
        }
      ]
    }
  ],
  "sourceType": "module",
  "range": [
    0,
    1012
  ],
  "loc": {
    "start": {
      "line": 1,
      "column": 0
    },
    "end": {
      "line": 23,
      "column": 1
    }
  },
  "comments": [
    {
      "type": "Block",
      "value": "*\r\n * Json builder. This builder give you the necessary tools to create a json bulk using our OpenGate REST.\r\n ",
      "range": [
        61,
        176
      ],
      "loc": {
        "start": {
          "line": 5,
          "column": 0
        },
        "end": {
          "line": 7,
          "column": 3
        }
      }
    },
    {
      "type": "Block",
      "value": "*\r\n     * @param {InternalOpenGateAPI} ogapi - required field. This is ogapi instance\r\n     * @param {string} organization - required field. This is the organization name where entities will be created, updated or deleted\r\n     * @param {resource} resource - required field. This is the resource used for the bulk provision\r\n     * @param {number} [timeout] - timeout in millisecons. The request will have a specific time out if it will be exceeded then the promise throw an exception\r\n     ",
      "range": [
        253,
        748
      ],
      "loc": {
        "start": {
          "line": 10,
          "column": 4
        },
        "end": {
          "line": 15,
          "column": 7
        }
      }
    }
  ]
}