{
  "type": "Program",
  "body": [
    {
      "type": "ExpressionStatement",
      "expression": {
        "type": "Literal",
        "value": "use strict",
        "raw": "'use strict'",
        "range": [
          0,
          12
        ],
        "loc": {
          "start": {
            "line": 1,
            "column": 0
          },
          "end": {
            "line": 1,
            "column": 12
          }
        }
      },
      "range": [
        0,
        13
      ],
      "loc": {
        "start": {
          "line": 1,
          "column": 0
        },
        "end": {
          "line": 1,
          "column": 13
        }
      }
    },
    {
      "type": "ImportDeclaration",
      "specifiers": [
        {
          "type": "ImportDefaultSpecifier",
          "local": {
            "type": "Identifier",
            "name": "SearchBuilder",
            "range": [
              22,
              35
            ],
            "loc": {
              "start": {
                "line": 3,
                "column": 7
              },
              "end": {
                "line": 3,
                "column": 20
              }
            }
          },
          "range": [
            22,
            35
          ],
          "loc": {
            "start": {
              "line": 3,
              "column": 7
            },
            "end": {
              "line": 3,
              "column": 20
            }
          }
        }
      ],
      "source": {
        "type": "Literal",
        "value": "./SearchBuilder",
        "raw": "'./SearchBuilder'",
        "range": [
          41,
          58
        ],
        "loc": {
          "start": {
            "line": 3,
            "column": 26
          },
          "end": {
            "line": 3,
            "column": 43
          }
        }
      },
      "range": [
        15,
        59
      ],
      "loc": {
        "start": {
          "line": 3,
          "column": 0
        },
        "end": {
          "line": 3,
          "column": 44
        }
      }
    },
    {
      "type": "ImportDeclaration",
      "specifiers": [
        {
          "type": "ImportDefaultSpecifier",
          "local": {
            "type": "Identifier",
            "name": "StaticSearch",
            "range": [
              67,
              79
            ],
            "loc": {
              "start": {
                "line": 4,
                "column": 7
              },
              "end": {
                "line": 4,
                "column": 19
              }
            }
          },
          "range": [
            67,
            79
          ],
          "loc": {
            "start": {
              "line": 4,
              "column": 7
            },
            "end": {
              "line": 4,
              "column": 19
            }
          }
        }
      ],
      "source": {
        "type": "Literal",
        "value": "../StaticSearch",
        "raw": "'../StaticSearch'",
        "range": [
          85,
          102
        ],
        "loc": {
          "start": {
            "line": 4,
            "column": 25
          },
          "end": {
            "line": 4,
            "column": 42
          }
        }
      },
      "range": [
        60,
        103
      ],
      "loc": {
        "start": {
          "line": 4,
          "column": 0
        },
        "end": {
          "line": 4,
          "column": 43
        }
      },
      "trailingComments": [
        {
          "type": "Block",
          "value": "*\n * Defined a search over ticket status catalog\n * @example ogapi.ticketStatusSearchBuilder()\n ",
          "range": [
            105,
            205
          ],
          "loc": {
            "start": {
              "line": 6,
              "column": 0
            },
            "end": {
              "line": 9,
              "column": 3
            }
          }
        }
      ]
    },
    {
      "type": "ExportDefaultDeclaration",
      "declaration": {
        "type": "ClassDeclaration",
        "id": {
          "type": "Identifier",
          "name": "TicketStatusSearchBuilder",
          "range": [
            227,
            252
          ],
          "loc": {
            "start": {
              "line": 10,
              "column": 21
            },
            "end": {
              "line": 10,
              "column": 46
            }
          }
        },
        "superClass": {
          "type": "Identifier",
          "name": "SearchBuilder",
          "range": [
            261,
            274
          ],
          "loc": {
            "start": {
              "line": 10,
              "column": 55
            },
            "end": {
              "line": 10,
              "column": 68
            }
          }
        },
        "body": {
          "type": "ClassBody",
          "body": [
            {
              "type": "MethodDefinition",
              "key": {
                "type": "Identifier",
                "name": "constructor",
                "range": [
                  380,
                  391
                ],
                "loc": {
                  "start": {
                    "line": 14,
                    "column": 4
                  },
                  "end": {
                    "line": 14,
                    "column": 15
                  }
                }
              },
              "value": {
                "type": "FunctionExpression",
                "id": null,
                "params": [
                  {
                    "type": "Identifier",
                    "name": "parent",
                    "range": [
                      392,
                      398
                    ],
                    "loc": {
                      "start": {
                        "line": 14,
                        "column": 16
                      },
                      "end": {
                        "line": 14,
                        "column": 22
                      }
                    }
                  }
                ],
                "body": {
                  "type": "BlockStatement",
                  "body": [
                    {
                      "type": "ExpressionStatement",
                      "expression": {
                        "type": "CallExpression",
                        "callee": {
                          "type": "Super",
                          "range": [
                            410,
                            415
                          ],
                          "loc": {
                            "start": {
                              "line": 15,
                              "column": 8
                            },
                            "end": {
                              "line": 15,
                              "column": 13
                            }
                          }
                        },
                        "arguments": [
                          {
                            "type": "Identifier",
                            "name": "parent",
                            "range": [
                              416,
                              422
                            ],
                            "loc": {
                              "start": {
                                "line": 15,
                                "column": 14
                              },
                              "end": {
                                "line": 15,
                                "column": 20
                              }
                            }
                          },
                          {
                            "type": "ObjectExpression",
                            "properties": [],
                            "range": [
                              424,
                              426
                            ],
                            "loc": {
                              "start": {
                                "line": 15,
                                "column": 22
                              },
                              "end": {
                                "line": 15,
                                "column": 24
                              }
                            }
                          }
                        ],
                        "range": [
                          410,
                          427
                        ],
                        "loc": {
                          "start": {
                            "line": 15,
                            "column": 8
                          },
                          "end": {
                            "line": 15,
                            "column": 25
                          }
                        }
                      },
                      "range": [
                        410,
                        428
                      ],
                      "loc": {
                        "start": {
                          "line": 15,
                          "column": 8
                        },
                        "end": {
                          "line": 15,
                          "column": 26
                        }
                      }
                    },
                    {
                      "type": "ExpressionStatement",
                      "expression": {
                        "type": "AssignmentExpression",
                        "operator": "=",
                        "left": {
                          "type": "MemberExpression",
                          "computed": false,
                          "object": {
                            "type": "ThisExpression",
                            "range": [
                              437,
                              441
                            ],
                            "loc": {
                              "start": {
                                "line": 16,
                                "column": 8
                              },
                              "end": {
                                "line": 16,
                                "column": 12
                              }
                            }
                          },
                          "property": {
                            "type": "Identifier",
                            "name": "_url",
                            "range": [
                              442,
                              446
                            ],
                            "loc": {
                              "start": {
                                "line": 16,
                                "column": 13
                              },
                              "end": {
                                "line": 16,
                                "column": 17
                              }
                            }
                          },
                          "range": [
                            437,
                            446
                          ],
                          "loc": {
                            "start": {
                              "line": 16,
                              "column": 8
                            },
                            "end": {
                              "line": 16,
                              "column": 17
                            }
                          }
                        },
                        "right": {
                          "type": "Literal",
                          "value": "/ticketStatus",
                          "raw": "'/ticketStatus'",
                          "range": [
                            449,
                            464
                          ],
                          "loc": {
                            "start": {
                              "line": 16,
                              "column": 20
                            },
                            "end": {
                              "line": 16,
                              "column": 35
                            }
                          }
                        },
                        "range": [
                          437,
                          464
                        ],
                        "loc": {
                          "start": {
                            "line": 16,
                            "column": 8
                          },
                          "end": {
                            "line": 16,
                            "column": 35
                          }
                        }
                      },
                      "range": [
                        437,
                        465
                      ],
                      "loc": {
                        "start": {
                          "line": 16,
                          "column": 8
                        },
                        "end": {
                          "line": 16,
                          "column": 36
                        }
                      }
                    },
                    {
                      "type": "ExpressionStatement",
                      "expression": {
                        "type": "AssignmentExpression",
                        "operator": "=",
                        "left": {
                          "type": "MemberExpression",
                          "computed": false,
                          "object": {
                            "type": "ThisExpression",
                            "range": [
                              474,
                              478
                            ],
                            "loc": {
                              "start": {
                                "line": 17,
                                "column": 8
                              },
                              "end": {
                                "line": 17,
                                "column": 12
                              }
                            }
                          },
                          "property": {
                            "type": "Identifier",
                            "name": "customFilters",
                            "range": [
                              479,
                              492
                            ],
                            "loc": {
                              "start": {
                                "line": 17,
                                "column": 13
                              },
                              "end": {
                                "line": 17,
                                "column": 26
                              }
                            }
                          },
                          "range": [
                            474,
                            492
                          ],
                          "loc": {
                            "start": {
                              "line": 17,
                              "column": 8
                            },
                            "end": {
                              "line": 17,
                              "column": 26
                            }
                          }
                        },
                        "right": {
                          "type": "ObjectExpression",
                          "properties": [],
                          "range": [
                            495,
                            497
                          ],
                          "loc": {
                            "start": {
                              "line": 17,
                              "column": 29
                            },
                            "end": {
                              "line": 17,
                              "column": 31
                            }
                          }
                        },
                        "range": [
                          474,
                          497
                        ],
                        "loc": {
                          "start": {
                            "line": 17,
                            "column": 8
                          },
                          "end": {
                            "line": 17,
                            "column": 31
                          }
                        }
                      },
                      "range": [
                        474,
                        498
                      ],
                      "loc": {
                        "start": {
                          "line": 17,
                          "column": 8
                        },
                        "end": {
                          "line": 17,
                          "column": 32
                        }
                      }
                    }
                  ],
                  "range": [
                    400,
                    504
                  ],
                  "loc": {
                    "start": {
                      "line": 14,
                      "column": 24
                    },
                    "end": {
                      "line": 18,
                      "column": 5
                    }
                  }
                },
                "generator": false,
                "expression": false,
                "range": [
                  391,
                  504
                ],
                "loc": {
                  "start": {
                    "line": 14,
                    "column": 15
                  },
                  "end": {
                    "line": 18,
                    "column": 5
                  }
                }
              },
              "kind": "constructor",
              "computed": false,
              "range": [
                380,
                504
              ],
              "loc": {
                "start": {
                  "line": 14,
                  "column": 4
                },
                "end": {
                  "line": 18,
                  "column": 5
                }
              },
              "leadingComments": [
                {
                  "type": "Block",
                  "value": "*\n     *  @param {!InternalOpenGateAPI} parent - Instance of our InternalOpenGateAPI\n     ",
                  "range": [
                    281,
                    375
                  ],
                  "loc": {
                    "start": {
                      "line": 11,
                      "column": 4
                    },
                    "end": {
                      "line": 13,
                      "column": 7
                    }
                  }
                }
              ],
              "trailingComments": [
                {
                  "type": "Block",
                  "value": "*\n     * Build a instance of StaticSearch \n     *\n     * @example\n     *   ogapi.ticketStatusSearchBuilder().build()\n     * @throws {SearchBuilderError} Throw error on url build\n     * @return {StaticSearch}  \n     ",
                  "range": [
                    510,
                    729
                  ],
                  "loc": {
                    "start": {
                      "line": 20,
                      "column": 4
                    },
                    "end": {
                      "line": 27,
                      "column": 7
                    }
                  }
                }
              ],
              "static": false
            },
            {
              "type": "MethodDefinition",
              "key": {
                "type": "Identifier",
                "name": "build",
                "range": [
                  734,
                  739
                ],
                "loc": {
                  "start": {
                    "line": 28,
                    "column": 4
                  },
                  "end": {
                    "line": 28,
                    "column": 9
                  }
                }
              },
              "value": {
                "type": "FunctionExpression",
                "id": null,
                "params": [],
                "body": {
                  "type": "BlockStatement",
                  "body": [
                    {
                      "type": "ReturnStatement",
                      "argument": {
                        "type": "NewExpression",
                        "callee": {
                          "type": "Identifier",
                          "name": "StaticSearch",
                          "range": [
                            763,
                            775
                          ],
                          "loc": {
                            "start": {
                              "line": 29,
                              "column": 19
                            },
                            "end": {
                              "line": 29,
                              "column": 31
                            }
                          }
                        },
                        "arguments": [
                          {
                            "type": "MemberExpression",
                            "computed": false,
                            "object": {
                              "type": "ThisExpression",
                              "range": [
                                776,
                                780
                              ],
                              "loc": {
                                "start": {
                                  "line": 29,
                                  "column": 32
                                },
                                "end": {
                                  "line": 29,
                                  "column": 36
                                }
                              }
                            },
                            "property": {
                              "type": "Identifier",
                              "name": "_parent",
                              "range": [
                                781,
                                788
                              ],
                              "loc": {
                                "start": {
                                  "line": 29,
                                  "column": 37
                                },
                                "end": {
                                  "line": 29,
                                  "column": 44
                                }
                              }
                            },
                            "range": [
                              776,
                              788
                            ],
                            "loc": {
                              "start": {
                                "line": 29,
                                "column": 32
                              },
                              "end": {
                                "line": 29,
                                "column": 44
                              }
                            }
                          },
                          {
                            "type": "CallExpression",
                            "callee": {
                              "type": "MemberExpression",
                              "computed": false,
                              "object": {
                                "type": "ThisExpression",
                                "range": [
                                  802,
                                  806
                                ],
                                "loc": {
                                  "start": {
                                    "line": 30,
                                    "column": 12
                                  },
                                  "end": {
                                    "line": 30,
                                    "column": 16
                                  }
                                }
                              },
                              "property": {
                                "type": "Identifier",
                                "name": "_buildUrl",
                                "range": [
                                  807,
                                  816
                                ],
                                "loc": {
                                  "start": {
                                    "line": 30,
                                    "column": 17
                                  },
                                  "end": {
                                    "line": 30,
                                    "column": 26
                                  }
                                }
                              },
                              "range": [
                                802,
                                816
                              ],
                              "loc": {
                                "start": {
                                  "line": 30,
                                  "column": 12
                                },
                                "end": {
                                  "line": 30,
                                  "column": 26
                                }
                              }
                            },
                            "arguments": [],
                            "range": [
                              802,
                              818
                            ],
                            "loc": {
                              "start": {
                                "line": 30,
                                "column": 12
                              },
                              "end": {
                                "line": 30,
                                "column": 28
                              }
                            }
                          },
                          {
                            "type": "Literal",
                            "value": null,
                            "raw": "null",
                            "range": [
                              832,
                              836
                            ],
                            "loc": {
                              "start": {
                                "line": 31,
                                "column": 12
                              },
                              "end": {
                                "line": 31,
                                "column": 16
                              }
                            }
                          },
                          {
                            "type": "MemberExpression",
                            "computed": false,
                            "object": {
                              "type": "MemberExpression",
                              "computed": false,
                              "object": {
                                "type": "ThisExpression",
                                "range": [
                                  850,
                                  854
                                ],
                                "loc": {
                                  "start": {
                                    "line": 32,
                                    "column": 12
                                  },
                                  "end": {
                                    "line": 32,
                                    "column": 16
                                  }
                                }
                              },
                              "property": {
                                "type": "Identifier",
                                "name": "_builderParams",
                                "range": [
                                  855,
                                  869
                                ],
                                "loc": {
                                  "start": {
                                    "line": 32,
                                    "column": 17
                                  },
                                  "end": {
                                    "line": 32,
                                    "column": 31
                                  }
                                }
                              },
                              "range": [
                                850,
                                869
                              ],
                              "loc": {
                                "start": {
                                  "line": 32,
                                  "column": 12
                                },
                                "end": {
                                  "line": 32,
                                  "column": 31
                                }
                              }
                            },
                            "property": {
                              "type": "Identifier",
                              "name": "timeout",
                              "range": [
                                870,
                                877
                              ],
                              "loc": {
                                "start": {
                                  "line": 32,
                                  "column": 32
                                },
                                "end": {
                                  "line": 32,
                                  "column": 39
                                }
                              }
                            },
                            "range": [
                              850,
                              877
                            ],
                            "loc": {
                              "start": {
                                "line": 32,
                                "column": 12
                              },
                              "end": {
                                "line": 32,
                                "column": 39
                              }
                            }
                          },
                          {
                            "type": "Literal",
                            "value": "ticketStatus",
                            "raw": "'ticketStatus'",
                            "range": [
                              891,
                              905
                            ],
                            "loc": {
                              "start": {
                                "line": 33,
                                "column": 12
                              },
                              "end": {
                                "line": 33,
                                "column": 26
                              }
                            }
                          },
                          {
                            "type": "MemberExpression",
                            "computed": false,
                            "object": {
                              "type": "ThisExpression",
                              "range": [
                                907,
                                911
                              ],
                              "loc": {
                                "start": {
                                  "line": 33,
                                  "column": 28
                                },
                                "end": {
                                  "line": 33,
                                  "column": 32
                                }
                              }
                            },
                            "property": {
                              "type": "Identifier",
                              "name": "customFilters",
                              "range": [
                                912,
                                925
                              ],
                              "loc": {
                                "start": {
                                  "line": 33,
                                  "column": 33
                                },
                                "end": {
                                  "line": 33,
                                  "column": 46
                                }
                              }
                            },
                            "range": [
                              907,
                              925
                            ],
                            "loc": {
                              "start": {
                                "line": 33,
                                "column": 28
                              },
                              "end": {
                                "line": 33,
                                "column": 46
                              }
                            }
                          }
                        ],
                        "range": [
                          759,
                          926
                        ],
                        "loc": {
                          "start": {
                            "line": 29,
                            "column": 15
                          },
                          "end": {
                            "line": 33,
                            "column": 47
                          }
                        }
                      },
                      "range": [
                        752,
                        927
                      ],
                      "loc": {
                        "start": {
                          "line": 29,
                          "column": 8
                        },
                        "end": {
                          "line": 33,
                          "column": 48
                        }
                      }
                    }
                  ],
                  "range": [
                    742,
                    933
                  ],
                  "loc": {
                    "start": {
                      "line": 28,
                      "column": 12
                    },
                    "end": {
                      "line": 34,
                      "column": 5
                    }
                  }
                },
                "generator": false,
                "expression": false,
                "range": [
                  739,
                  933
                ],
                "loc": {
                  "start": {
                    "line": 28,
                    "column": 9
                  },
                  "end": {
                    "line": 34,
                    "column": 5
                  }
                }
              },
              "kind": "method",
              "computed": false,
              "range": [
                734,
                933
              ],
              "loc": {
                "start": {
                  "line": 28,
                  "column": 4
                },
                "end": {
                  "line": 34,
                  "column": 5
                }
              },
              "leadingComments": [
                {
                  "type": "Block",
                  "value": "*\n     * Build a instance of StaticSearch \n     *\n     * @example\n     *   ogapi.ticketStatusSearchBuilder().build()\n     * @throws {SearchBuilderError} Throw error on url build\n     * @return {StaticSearch}  \n     ",
                  "range": [
                    510,
                    729
                  ],
                  "loc": {
                    "start": {
                      "line": 20,
                      "column": 4
                    },
                    "end": {
                      "line": 27,
                      "column": 7
                    }
                  }
                }
              ],
              "static": false
            }
          ],
          "range": [
            275,
            937
          ],
          "loc": {
            "start": {
              "line": 10,
              "column": 69
            },
            "end": {
              "line": 37,
              "column": 1
            }
          }
        },
        "range": [
          221,
          937
        ],
        "loc": {
          "start": {
            "line": 10,
            "column": 15
          },
          "end": {
            "line": 37,
            "column": 1
          }
        },
        "leadingComments": [
          {
            "type": "Block",
            "value": "*\n * Defined a search over ticket status catalog\n * @example ogapi.ticketStatusSearchBuilder()\n ",
            "range": [
              105,
              205
            ],
            "loc": {
              "start": {
                "line": 6,
                "column": 0
              },
              "end": {
                "line": 9,
                "column": 3
              }
            }
          }
        ],
        "trailingComments": []
      },
      "range": [
        206,
        937
      ],
      "loc": {
        "start": {
          "line": 10,
          "column": 0
        },
        "end": {
          "line": 37,
          "column": 1
        }
      },
      "leadingComments": [
        {
          "type": "Block",
          "value": "*\n * Defined a search over ticket status catalog\n * @example ogapi.ticketStatusSearchBuilder()\n ",
          "range": [
            105,
            205
          ],
          "loc": {
            "start": {
              "line": 6,
              "column": 0
            },
            "end": {
              "line": 9,
              "column": 3
            }
          }
        }
      ]
    }
  ],
  "sourceType": "module",
  "range": [
    0,
    937
  ],
  "loc": {
    "start": {
      "line": 1,
      "column": 0
    },
    "end": {
      "line": 37,
      "column": 1
    }
  },
  "comments": [
    {
      "type": "Block",
      "value": "*\n * Defined a search over ticket status catalog\n * @example ogapi.ticketStatusSearchBuilder()\n ",
      "range": [
        105,
        205
      ],
      "loc": {
        "start": {
          "line": 6,
          "column": 0
        },
        "end": {
          "line": 9,
          "column": 3
        }
      }
    },
    {
      "type": "Block",
      "value": "*\n     *  @param {!InternalOpenGateAPI} parent - Instance of our InternalOpenGateAPI\n     ",
      "range": [
        281,
        375
      ],
      "loc": {
        "start": {
          "line": 11,
          "column": 4
        },
        "end": {
          "line": 13,
          "column": 7
        }
      }
    },
    {
      "type": "Block",
      "value": "*\n     * Build a instance of StaticSearch \n     *\n     * @example\n     *   ogapi.ticketStatusSearchBuilder().build()\n     * @throws {SearchBuilderError} Throw error on url build\n     * @return {StaticSearch}  \n     ",
      "range": [
        510,
        729
      ],
      "loc": {
        "start": {
          "line": 20,
          "column": 4
        },
        "end": {
          "line": 27,
          "column": 7
        }
      }
    }
  ]
}